testmd/__init__.py
testmd-0.0.2.data/scripts/testmdcli
testmd-0.0.2.dist-info/LICENSE
testmd-0.0.2.dist-info/METADATA
testmd-0.0.2.dist-info/WHEEL
testmd-0.0.2.dist-info/top_level.txt
testmd-0.0.2.dist-info/RECORD
