Metadata-Version: 2.1
Name: testmd
Version: 0.0.2
Summary: A simple tool to test markdown front matter yaml
Home-page: https://github.com/sellorm/mdtest
Author: Mark Sellors
Author-email: python@5vcc.com
License: UNKNOWN
Platform: UNKNOWN
Classifier: Programming Language :: Python :: 3
Classifier: License :: OSI Approved :: MIT License
Classifier: Operating System :: OS Independent
Requires-Python: >=3.6
Requires-Dist: python-frontmatter (>=0.5.0)
